MANIFEST.in
README.md
setup.py
treeapp/__init__.py
treeapp/admin.py
treeapp/apps.py
treeapp/models.py
treeapp/tests.py
treeapp/views.py
treeapp.egg-info/PKG-INFO
treeapp.egg-info/SOURCES.txt
treeapp.egg-info/dependency_links.txt
treeapp.egg-info/requires.txt
treeapp.egg-info/top_level.txt
treeapp/migrations/0001_initial.py
treeapp/migrations/__init__.py